licensing/__init__.py
licensing/apps.py
licensing/fields.py
licensing/fixtures/creativecommons.json.gz
licensing/locale/README.md
licensing/migrations/0001_initial.py
licensing/migrations/0002_alter_license_options_remove_license_url_and_more.py
licensing/migrations/__init__.py
licensing/models.py
licensing/templates/licensing/snippet.html
licensing/utils.py
django_content_license-0.2.3.dist-info/AUTHORS.md
django_content_license-0.2.3.dist-info/LICENSE
django_content_license-0.2.3.dist-info/METADATA
django_content_license-0.2.3.dist-info/WHEEL
django_content_license-0.2.3.dist-info/RECORD
