Metadata-Version: 2.1
Name: django-content-license
Version: 0.2.3
Summary: Store license information alongside your Django data models
Home-page: https://github.com/SamuelJennings/django-content-license
License: MIT
Keywords: django,research,science,datasets,research management,open source,open science,FAIR
Author: Sam Jennings
Requires-Python: >=3.10,<4.0
Classifier: Development Status :: 3 - Alpha
Classifier: Framework :: Django :: 3.2
Classifier: Framework :: Django :: 4.0
Classifier: Intended Audience :: Developers
Classifier: License :: OSI Approved :: BSD License
Classifier: License :: OSI Approved :: MIT License
Classifier: Natural Language :: English
Classifier: Programming Language :: Python :: 3
Classifier: Programming Language :: Python :: 3.10
Classifier: Programming Language :: Python :: 3.11
Classifier: Programming Language :: Python :: 3.12
Requires-Dist: django (>=3.2)
